{
  "metadata": {
    "user": "atf",
    "date": "2025-11-12T13:20:32.627497",
    "hardware_id": "Ashas-lvmxxr-u",
    "cpu_arch": "x86_64",
    "ram": "30.9GB",
    "python_version": "3.11.14"
  },
  "hash_run": "892f9d328ff838b1004a4b30b2b5999ab7ea2020fd47e0cd49bd86c589cc7d1b",
  "hash_config": "5071cc3d90efe31477904f7eaeb5ab869a8a546684a9c745860b789e1a06d381",
  "config": {
    "instance_name": "C101",
    "solver_name": "simulated_annealing",
    "seed": 47,
    "parameters": {
      "max_time": 300,
      "max_iterations": 50000,
      "max_iterations_no_improvement": 1000,
      "record_convergence": true,
      "verbose": true,
      "seed": null,
      "name": "simulated_annealing",
      "initial_temperature": 2000,
      "cooling_rate": 0.9995,
      "min_temperature": 0.001,
      "reheating": false,
      "reheating_interval": 1000,
      "reheating_factor": 1.5,
      "validate_neighbors": true
    }
  },
  "results": {
    "time_seconds": 0.13624119758605957,
    "n_iterations": 1000,
    "cost": 1010.4000000000001,
    "solution": [
      [
        13,
        15,
        11,
        9,
        6,
        4,
        2,
        1,
        75
      ],
      [
        5,
        3,
        7,
        8,
        10
      ],
      [
        17,
        18,
        19,
        16,
        14,
        12
      ],
      [
        20,
        24,
        25,
        27,
        29,
        30,
        28,
        26,
        23,
        22,
        21
      ],
      [
        32,
        33,
        35,
        37,
        38,
        39,
        36,
        34
      ],
      [
        43,
        42,
        40,
        44,
        46
      ],
      [
        31,
        45,
        48,
        51,
        50,
        52,
        49,
        47
      ],
      [
        57,
        55,
        54,
        53,
        56,
        58,
        60,
        59
      ],
      [
        67,
        63
      ],
      [
        65,
        41,
        62,
        74,
        72,
        61,
        64,
        68,
        66,
        69
      ],
      [
        81,
        78,
        76,
        71,
        70,
        73,
        77,
        79,
        80
      ],
      [
        90,
        87,
        86,
        83,
        82,
        84,
        85,
        88,
        89,
        91
      ],
      [
        98,
        96,
        95,
        94,
        92,
        93,
        97,
        100,
        99
      ]
    ],
    "convergence": [
      {
        "iteration": 0,
        "cost": 1010.3999999999996
      },
      {
        "iteration": 1000,
        "cost": 1010.3999999999996
      }
    ],
    "additional_info": {
      "initial_cost": 1010.4000000000001,
      "n_vehicles": 13,
      "improvement": 4.547473508864641e-13,
      "improvement_pct": 4.500666576469359e-14,
      "constructor": "savings_parallel",
      "solver_name": "SimulatedAnnealingSolver",
      "final_cost": 1010.3999999999996,
      "iterations": 1000,
      "time_seconds": 0.1363210678100586,
      "accepted_moves": 1000,
      "rejected_moves": 0,
      "acceptance_rate": 1.0,
      "iterations_per_second": 7335.623290402468,
      "final_temperature": 1212.9096456801926,
      "initial_temperature": 2000,
      "cooling_rate": 0.9995,
      "invalid_neighbors": 0,
      "invalid_neighbor_rate": 0.0
    }
  }
}